fotmob/__init__.py
fotmob/fotmob.py
fotmob/myfunctions.py
python_fotmob_wrapper-0.1.8.dist-info/LICENSE
python_fotmob_wrapper-0.1.8.dist-info/METADATA
python_fotmob_wrapper-0.1.8.dist-info/WHEEL
python_fotmob_wrapper-0.1.8.dist-info/top_level.txt
python_fotmob_wrapper-0.1.8.dist-info/RECORD
