Metadata-Version: 2.1
Name: python-fotmob-wrapper
Version: 0.1.8
Summary: Python wrapper for Fotmob
Home-page: https://github.com/AndyReifman/fotmob
Author: Andrew Reifman-Packett
Author-email: reifmanpackett@gmail.com
License: UNKNOWN
Project-URL: Bug Tracker, https://github.com/AndyReifman/fotmob/issues
Platform: UNKNOWN
Classifier: Programming Language :: Python :: 3
Classifier: License :: OSI Approved :: MIT License
Classifier: Operating System :: OS Independent
License-File: LICENSE
